LICENSE.txt
README.rst
setup.py
pack_dataset/__init__.py
pack_dataset/custom_exception.py
pack_dataset/dataset_loader.py
pack_dataset.egg-info/PKG-INFO
pack_dataset.egg-info/SOURCES.txt
pack_dataset.egg-info/dependency_links.txt
pack_dataset.egg-info/requires.txt
pack_dataset.egg-info/top_level.txt