Metadata-Version: 2.1
Name: pack-dataset
Version: 1.1.6
Summary: This project contains a loader of a special data set, as a connection to the database using pymssql
Home-page: https://github.com/lnetw/pack_dataset
Author: Maxim Ermak
Author-email: 
License: MIT License (MIT)
Platform: UNKNOWN
Classifier: Programming Language :: Python :: 3.8
License-File: LICENSE.txt
